[
    {
        "id": 1,
        "title": "Test Event 1",
        "time": "2024-04-17 13:13:47",
        "location": "Islamabad",
        "category": "Category 1",
        "rank": 1,
        "liked": true,
        "description": "Lorem ipsum, dolor sit amet consectetur adipisicing elit. Fugiat quasi asperiores aspernatur quis amet voluptates deserunt quaerat eligendi atque nihil! Esse consequatur voluptatum error aperiam cupiditate voluptatem officia facere dolorum!"
    },
    {
        "id": 2,
        "title": "Test Event 2",
        "time": "2024-04-17 13:13:47",
        "location": "Islamabad",
        "category": "Category 1",
        "rank": 1,
        "liked": false,
        "description": "Lorem ipsum, dolor sit amet consectetur adipisicing elit. Fugiat quasi asperiores aspernatur quis amet voluptates deserunt quaerat eligendi atque nihil! Esse consequatur voluptatum error aperiam cupiditate voluptatem officia facere dolorum!"
    },
    {
        "id": 3,
        "title": "Test Event 3",
        "time": "2024-04-17 13:13:47",
        "location": "Islamabad",
        "category": "Category 2",
        "rank": 1,
        "liked": true,
        "description": "Lorem ipsum, dolor sit amet consectetur adipisicing elit. Fugiat quasi asperiores aspernatur quis amet voluptates deserunt quaerat eligendi atque nihil! Esse consequatur voluptatum error aperiam cupiditate voluptatem officia facere dolorum!"
    },
    {
        "id": 4,
        "title": "Test Event 4",
        "time": "2024-04-17 13:13:47",
        "location": "Islamabad",
        "category": "Category 2",
        "rank": 1,
        "liked": false,
        "description": "Lorem ipsum, dolor sit amet consectetur adipisicing elit. Fugiat quasi asperiores aspernatur quis amet voluptates deserunt quaerat eligendi atque nihil! Esse consequatur voluptatum error aperiam cupiditate voluptatem officia facere dolorum!"
    },
    {
        "id": 5,
        "title": "Test Event 1",
        "time": "2024-04-17 13:13:47",
        "location": "Islamabad",
        "category": "Category 1",
        "rank": 1,
        "liked": false,
        "description": "Lorem ipsum, dolor sit amet consectetur adipisicing elit. Fugiat quasi asperiores aspernatur quis amet voluptates deserunt quaerat eligendi atque nihil! Esse consequatur voluptatum error aperiam cupiditate voluptatem officia facere dolorum!"
    },
    {
        "id": 6,
        "title": "Test Event 1",
        "time": "2024-04-17 13:13:47",
        "location": "Islamabad",
        "category": "Category 1",
        "rank": 1,
        "liked": true,
        "description": "Lorem ipsum, dolor sit amet consectetur adipisicing elit. Fugiat quasi asperiores aspernatur quis amet voluptates deserunt quaerat eligendi atque nihil! Esse consequatur voluptatum error aperiam cupiditate voluptatem officia facere dolorum!"
    },
    {
        "id": 7,
        "title": "Test Event 1",
        "time": "2024-04-17 13:13:47",
        "location": "Islamabad",
        "category": "Category 1",
        "rank": 1,
        "liked": false,
        "description": "Lorem ipsum, dolor sit amet consectetur adipisicing elit. Fugiat quasi asperiores aspernatur quis amet voluptates deserunt quaerat eligendi atque nihil! Esse consequatur voluptatum error aperiam cupiditate voluptatem officia facere dolorum!"
    },
    {
        "id": 8,
        "title": "Test Event 1",
        "time": "2024-04-17 13:13:47",
        "location": "Islamabad",
        "category": "Category 1",
        "rank": 1,
        "liked": false,
        "description": "Lorem ipsum, dolor sit amet consectetur adipisicing elit. Fugiat quasi asperiores aspernatur quis amet voluptates deserunt quaerat eligendi atque nihil! Esse consequatur voluptatum error aperiam cupiditate voluptatem officia facere dolorum!"
    },
    {
        "id": 9,
        "title": "Test Event 1",
        "time": "2024-04-17 13:13:47",
        "location": "Islamabad",
        "category": "Category 1",
        "rank": 1,
        "liked": false,
        "description": "Lorem ipsum, dolor sit amet consectetur adipisicing elit. Fugiat quasi asperiores aspernatur quis amet voluptates deserunt quaerat eligendi atque nihil! Esse consequatur voluptatum error aperiam cupiditate voluptatem officia facere dolorum!"
    },
    {
        "id": 10,
        "title": "Test Event 1",
        "time": "2024-04-17 13:13:47",
        "location": "Islamabad",
        "category": "Category 1",
        "rank": 1,
        "liked": true,
        "description": "Lorem ipsum, dolor sit amet consectetur adipisicing elit. Fugiat quasi asperiores aspernatur quis amet voluptates deserunt quaerat eligendi atque nihil! Esse consequatur voluptatum error aperiam cupiditate voluptatem officia facere dolorum!"
    },
    {
        "id": 11,
        "title": "Test Event 1",
        "time": "2024-04-17 13:13:47",
        "location": "Islamabad",
        "category": "Category 1",
        "rank": 1,
        "liked": true,
        "description": "Lorem ipsum, dolor sit amet consectetur adipisicing elit. Fugiat quasi asperiores aspernatur quis amet voluptates deserunt quaerat eligendi atque nihil! Esse consequatur voluptatum error aperiam cupiditate voluptatem officia facere dolorum!"
    }
]